yamlenc/__init__.py
yamlenc/dump.py
yamlenc/yamlenc.py
yamlenc-0.5.dist-info/DESCRIPTION.rst
yamlenc-0.5.dist-info/METADATA
yamlenc-0.5.dist-info/RECORD
yamlenc-0.5.dist-info/WHEEL
yamlenc-0.5.dist-info/entry_points.txt
yamlenc-0.5.dist-info/metadata.json
yamlenc-0.5.dist-info/top_level.txt
